HISTORY.rst
LICENSE
MANIFEST.in
README.rst
requirements-tests.txt
requirements.txt
setup.py
xmake/__init__.py
xmake/dep.py
xmake/dsl.py
xmake/executor.py
xmake.egg-info/PKG-INFO
xmake.egg-info/SOURCES.txt
xmake.egg-info/dependency_links.txt
xmake.egg-info/requires.txt
xmake.egg-info/top_level.txt
xmake/op/__init__.py
xmake/op/abstract.py
xmake/op/docker.py