Metadata-Version: 1.1
Name: xmake
Version: 0.0.1a3
Summary: Python 3 make-like DSL
Home-page: https://github.com/andreycizov/python-xmake
Author: Andrey Cizov
Author-email: acizov@gmail.com
License: UNKNOWN
Platform: UNKNOWN
Classifier: Development Status :: 2 - Pre-Alpha
Classifier: Intended Audience :: Developers
Classifier: License :: OSI Approved :: Apache Software License
Classifier: Natural Language :: English
Classifier: Programming Language :: Python :: 3.6
